fastapi_opa/__init__.py
fastapi_opa/auth/__init__.py
fastapi_opa/auth/auth_api_key.py
fastapi_opa/auth/auth_interface.py
fastapi_opa/auth/auth_oidc.py
fastapi_opa/auth/auth_saml.py
fastapi_opa/auth/exceptions.py
fastapi_opa/opa/__init__.py
fastapi_opa/opa/enrichment/__init__.py
fastapi_opa/opa/enrichment/graphql_enrichment.py
fastapi_opa/opa/opa_config.py
fastapi_opa/opa/opa_middleware.py
fastapi_opa-2.0.3.dist-info/LICENSE
fastapi_opa-2.0.3.dist-info/METADATA
fastapi_opa-2.0.3.dist-info/WHEEL
fastapi_opa-2.0.3.dist-info/RECORD
