Metadata-Version: 2.1
Name: fastapi-opa
Version: 2.0.3
Summary: Fastapi OPA middleware incl. auth flow.
Home-page: https://github.com/busykoala/fastapi-opa
License: GPL-3.0-or-later
Keywords: fastapi,oidc,authentication,authorization,saml
Author: Matthias Osswald
Author-email: info@busykoala.io
Requires-Python: >=3.8,<4.0
Classifier: License :: OSI Approved :: GNU General Public License v3 or later (GPLv3+)
Classifier: Programming Language :: Python :: 3
Classifier: Programming Language :: Python :: 3.8
Classifier: Programming Language :: Python :: 3.9
Classifier: Programming Language :: Python :: 3.10
Classifier: Programming Language :: Python :: 3.11
Classifier: Programming Language :: Python :: 3.12
Classifier: Programming Language :: Python :: 3.13
Provides-Extra: graphql
Provides-Extra: saml
Requires-Dist: PyJWT[crypto] (>=2.4)
Requires-Dist: fastapi (>=0.109.2)
Requires-Dist: graphene (>=2,<3) ; extra == "graphql"
Requires-Dist: itsdangerous
Requires-Dist: python-multipart ; extra == "saml"
Requires-Dist: python3-saml ; extra == "saml"
Requires-Dist: requests
Project-URL: Repository, https://github.com/busykoala/fastapi-opa
